MANIFEST.in
README.md
setup.py
ThreadedTree.egg-info/PKG-INFO
ThreadedTree.egg-info/SOURCES.txt
ThreadedTree.egg-info/dependency_links.txt
ThreadedTree.egg-info/top_level.txt
threadedtree/__init__.py
threadedtree/bidirectionaliterator.py
threadedtree/threadedtree.py
threadedtree/treenodes.py
threadedtree/tests/__init__.py
threadedtree/tests/test_bidirectional_iterator_unbalanced_TBST.py
threadedtree/tests/test_tree_nodes.py
threadedtree/tests/test_unbalanced_threaded_bst.py