Metadata-Version: 1.0
Name: ThreadedTree
Version: 1.0.dev2
Summary: A carefully implemented double threaded binary search tree in pure python.
Home-page: http://tylerspringer.com/
Author: M Tyler Springer
Author-email: mspringer@smu.edu
License: GNU Lesser General Public License v3.0
Platform: UNKNOWN
